{
    "California": 39512223,
    "Texas": 28995881,
    "Florida": 21477737,
    "New York": 19453561,
    "Pennsylvania": 12801989,
    "Illinois": 12671821,
    "Ohio": 11689100,
    "Georgia (us)": 10617423,
    "North Carolina": 10488084,
    "Michigan": 9986857,
    "New Jersey": 8882190,
    "Virginia": 8535519,
    "Washington": 7614893,
    "Arizona": 7278717,
    "Massachusetts": 6949503,
    "Tennessee": 6833174,
    "Indiana": 6732219,
    "Missouri": 6137428,
    "Maryland": 6045680,
    "Wisconsin": 5822434,
    "Colorado": 5758736,
    "Minnesota": 5639632,
    "South Carolina": 5148714,
    "Alabama": 4903185,
    "Louisiana": 4648794,
    "Kentucky": 4467673,
    "Oregon": 4217737,
    "Oklahoma": 3956971,
    "Connecticut": 3565287,
    "Utah": 3205958,
    "Iowa": 3155070,
    "Nevada": 3080156,
    "Arkansas": 3017825,
    "Mississippi": 2976149,
    "Kansas": 2913314,
    "New Mexico": 2096829,
    "Nebraska": 1934408,
    "Idaho": 1787065,
    "West Virginia": 1792147,
    "Hawaii": 1415872,
    "New Hampshire": 1359711,
    "Maine": 1344212,
    "Montana": 1068778,
    "Rhode Island": 1059361,
    "Delaware": 973764,
    "South Dakota": 884659,
    "North Dakota": 762062,
    "Alaska": 731545,
    "District of Columbia": 705749,
    "Vermont": 623989,
    "Wyoming": 578759,
    "U.S. Virgin Islands": 104914,
    "American Samoa": 55641,
    "Afghanistan": 37172386,
    "Albania": 2866376,
    "Algeria": 42228429,
    "Andorra": 77006,
    "Angola": 30809762,
    "Anguilla": 15094,
    "Antigua and Barbuda": 96286,
    "Argentina": 44494502,
    "Armenia": 2951776,
    "Aruba": 105845,
    "Australia": 24982688,
    "Austria": 8840521,
    "Azerbaijan": 9939800,
    "Bahamas": 385640,
    "Bahrain": 1569439,
    "Bangladesh": 161356039,
    "Barbados": 286641,
    "Belarus": 9483499,
    "Belgium": 11433256,
    "Belize": 383071,
    "Benin": 11485048,
    "Bermuda": 63973,
    "Bhutan": 754394,
    "Bolivia": 11353142,
    "Bosnia and Herzegovina": 3323929,
    "Botswana": 2254126,
    "Brazil": 209469333,
    "Brunei": 428962,
    "Bulgaria": 7025037,
    "Burkina Faso": 19751535,
    "Burundi": 11175378,
    "Cambodia": 16249798,
    "Cameroon": 25216237,
    "Canada": 37057765,
    "Cape Verde": 543767,
    "Cayman Islands": 64174,
    "Central African Republic": 4666377,
    "Chad": 15477751,
    "Chile": 18729160,
    "China": 1392730000,
    "Colombia": 49648685,
    "Congo": 5244363,
    "Costa Rica": 4999441,
    "Croatia": 4087843,
    "Cuba": 11338138,
    "Cyprus": 1189265,
    "Czech Republic": 10629928,
    "Denmark": 5793636,
    "Djibouti": 958920,
    "Dominica": 71625,
    "Dominican Republic": 10627165,
    "Ecuador": 17084357,
    "Egypt": 98423595,
    "El Salvador": 6420744,
    "Equatorial Guinea": 1308974,
    "Eritrea": 3213972,
    "Estonia": 1321977,
    "Ethiopia": 109224559,
    "Falkland Islands": 2840,
    "Fiji": 883483,
    "Finland": 5515525,
    "France": 66977107,
    "French Polynesia": 277679,
    "Gabon": 2119275,
    "Gambia": 2280102,
    "Georgia": 3726549,
    "Germany": 82905782,
    "Ghana": 29767108,
    "Gibraltar": 33718,
    "Greece": 10731726,
    "Greenland": 56025,
    "Grenada": 111454,
    "Guam": 165768,
    "Guatemala": 17247807,
    "Guinea": 12414318,
    "Guinea-Bissau": 1874309,
    "Guyana": 779004,
    "Haiti": 11123176,
    "Vatican": 825,
    "Honduras": 9587522,
    "Hong Kong": 7451000,
    "Hungary": 9775564,
    "Iceland": 352721,
    "India": 1352617328,
    "Indonesia": 267663435,
    "Iran": 81800269,
    "Iraq": 38433600,
    "Ireland": 4867309,
    "Israel": 8882800,
    "Italy": 60421760,
    "Jamaica": 2934855,
    "Japan": 126529100,
    "Jordan": 9956011,
    "Kazakhstan": 18272430,
    "Kenya": 51393010,
    "Kuwait": 4137309,
    "Kyrgyzstan": 6322800,
    "Laos": 7061507,
    "Latvia": 1927174,
    "Lebanon": 6848925,
    "Liberia": 4818977,
    "Libya": 6678567,
    "Liechtenstein": 37910,
    "Lithuania": 2801543,
    "Luxembourg": 607950,
    "Madagascar": 26262368,
    "Malawi": 18143315,
    "Malaysia": 31528585,
    "Maldives": 515696,
    "Mali": 19077690,
    "Malta": 484630,
    "Mauritania": 4403319,
    "Mauritius": 1265303,
    "Mexico": 126190788,
    "Moldova": 2706049,
    "Monaco": 38682,
    "Mongolia": 3170208,
    "Montenegro": 631219,
    "Montserrat": 5900,
    "Morocco": 36029138,
    "Mozambique": 29495962,
    "Myanmar": 53708395,
    "Namibia": 2448255,
    "Nepal": 28087871,
    "Netherlands": 17231624,
    "New Caledonia": 284060,
    "New Zealand": 4841000,
    "Nicaragua": 6465513,
    "Niger": 22442948,
    "Nigeria": 195874740,
    "Northern Mariana Islands": 56882,
    "Norway": 5311916,
    "Oman": 4829483,
    "Pakistan": 212215030,
    "Palestine": 4569087,
    "Panama": 4176873,
    "Papua New Guinea": 8606316,
    "Paraguay": 6956071,
    "Peru": 31989256,
    "Philippines": 106651922,
    "Poland": 37974750,
    "Portugal": 10283822,
    "Puerto Rico": 3195153,
    "Qatar": 2781677,
    "Romania": 19466145,
    "Russia": 144478050,
    "Rwanda": 12301939,
    "Saint Helena": 6600,
    "Saint Kitts and Nevis": 52441,
    "Saint Lucia": 181889,
    "Saint Pierre and Miquelon": 5888,
    "Saint Vincent and the Grenadines": 110210,
    "Samoa": 196130,
    "San Marino": 33785,
    "Sao Tome and Principe": 211028,
    "Saudi Arabia": 33699947,
    "Senegal": 15854360,
    "Seychelles": 96762,
    "Sierra Leone": 7650154,
    "Singapore": 5638676,
    "Slovakia": 5446771,
    "Slovenia": 2073894,
    "Somalia": 15008154,
    "South Africa": 57779622,
    "South Korea": 51606633,
    "South Sudan": 10975920,
    "Spain": 46796540,
    "SriLanka": 21670000,
    "Sudan": 41801533,
    "Suriname": 575991,
    "Swaziland": 1136191,
    "Sweden": 10175214,
    "Switzerland": 8513227,
    "Syria": 16906283,
    "Tanzania": 56318348,
    "Thailand": 69428524,
    "Togo": 7889094,
    "Trinidad and Tobago": 1389858,
    "Tunisia": 11565204,
    "Turkey": 82319724,
    "Turks and Caicos Islands": 37665,
    "Uganda": 42723139,
    "Ukraine": 44622516,
    "United Arab Emirates": 9630959,
    "United Kingdom": 66460344,
    "United States": 326687501,
    "Uruguay": 3449299,
    "Uzbekistan": 32955400,
    "Venezuela": 28870195,
    "Vietnam": 95540395,
    "Yemen": 28498687,
    "Zambia": 17351822,
    "Zimbabwe": 14439018
}